monke/__init__.py
monke/client.py
monke/common.py
monke/server.py
monke-1.0.12.dist-info/LICENSE
monke-1.0.12.dist-info/METADATA
monke-1.0.12.dist-info/WHEEL
monke-1.0.12.dist-info/top_level.txt
monke-1.0.12.dist-info/RECORD
