Metadata-Version: 2.1
Name: monke
Version: 1.0.12
Summary: monke - event-based socket wrapper
Home-page: https://github.com/husseinraed/monke
Author: Hussein Raed
Author-email: me@husseinraed.cf
License: UNKNOWN
Platform: UNKNOWN
Classifier: Programming Language :: Python :: 3
Classifier: License :: OSI Approved :: MIT License
Classifier: Operating System :: OS Independent
Requires-Python: >=3.6
